llm_rs_metal-0.2.15.dist-info/METADATA
llm_rs_metal-0.2.15.dist-info/WHEEL
llm_rs_metal-0.2.15.dist-info/license_files/LICENSE
llm_rs/llm_rs.pyi
llm_rs/langchain/__init__.py
llm_rs/langchain/langchain.py
llm_rs/__init__.py
llm_rs/base_model.py
llm_rs/results.pyi
llm_rs/haystack/haystack.py
llm_rs/haystack/__init__.py
llm_rs/models.pyi
llm_rs/py.typed
llm_rs/config.pyi
llm_rs/repository.py
llm_rs/convert/__init__.py
llm_rs/convert/models/_base.py
llm_rs/convert/models/gpt2.py
llm_rs/convert/models/gptj.py
llm_rs/convert/models/__init__.py
llm_rs/convert/models/llama.py
llm_rs/convert/models/mpt.py
llm_rs/convert/models/gptneox.py
llm_rs/convert/models/bloom.py
llm_rs/convert/auto_converter.py
llm_rs/auto.py
llm_rs/llm_rs.abi3.so
llm_rs_metal-0.2.15.dist-info/RECORD
