Metadata-Version: 2.1
Name: llm-rs-metal
Version: 0.2.15
Classifier: Programming Language :: Rust
Classifier: Programming Language :: Python :: Implementation :: CPython
Classifier: Programming Language :: Python :: Implementation :: PyPy
Classifier: Programming Language :: Python :: 3
Classifier: License :: OSI Approved :: MIT License
Requires-Dist: blake3
Requires-Dist: huggingface-hub >= 0.14.1
Requires-Dist: langchain>=0.0.266; extra == 'langchain'
Requires-Dist: transformers >= 4.29.0; extra == 'convert'
Requires-Dist: sentencepiece >= 0.1.99; extra == 'convert'
Requires-Dist: torch >= 2.0.0; extra == 'convert'
Requires-Dist: accelerate >= 0.19.0; extra == 'convert'
Requires-Dist: tqdm; extra == 'convert'
Requires-Dist: einops >= 0.6.1; extra == 'convert'
Requires-Dist: farm-haystack>=1.17.1; extra == 'haystack'
Provides-Extra: langchain
Provides-Extra: convert
Provides-Extra: haystack
License-File: LICENSE
Summary: Unofficial python bindings for llm-rs. 🐍❤️🦀
Keywords: LLM,Transformers
Author: Lukas Kreussel
Requires-Python: >=3.8
Project-URL: documentation, https://llukas22.github.io/llm-rs-python/
Project-URL: repository, https://github.com/LLukas22/llm-rs-python
